flamehaven_tensor_canon-0.1.3.dist-info/licenses/LICENSE
tensor_canon/__init__.py
tensor_canon/canon_prime.py
tensor_canon/covenant.py
tensor_canon/resonance.py
tensor_canon/validator.py
tensor_canon/backends/base.py
tensor_canon/backends/numpy_backend.py
tensor_canon/backends/torch_backend.py
flamehaven_tensor_canon-0.1.3.dist-info/METADATA
flamehaven_tensor_canon-0.1.3.dist-info/WHEEL
flamehaven_tensor_canon-0.1.3.dist-info/top_level.txt
flamehaven_tensor_canon-0.1.3.dist-info/RECORD
