Metadata-Version: 2.4
Name: flamehaven-tensor-canon
Version: 0.1.3
Summary: Universal tensor validation and drift detection for PyTorch (NumPy optional).
Author-email: Flamehaven Sovereign Core <core@flamehaven.ai>
License-Expression: MIT
Keywords: pytorch,numpy,validation,drift-detection,mmd
Classifier: Development Status :: 4 - Beta
Classifier: Intended Audience :: Developers
Classifier: Programming Language :: Python :: 3.10
Classifier: Programming Language :: Python :: 3.11
Classifier: Programming Language :: Python :: 3.12
Classifier: Topic :: Scientific/Engineering :: Artificial Intelligence
Classifier: Topic :: Software Development :: Libraries
Classifier: Topic :: Software Development :: Libraries :: Python Modules
Requires-Python: >=3.10
License-File: LICENSE
Requires-Dist: torch>=2.0.0
Provides-Extra: numpy
Requires-Dist: numpy>=1.20.0; extra == "numpy"
Provides-Extra: dev
Requires-Dist: pytest; extra == "dev"
Requires-Dist: ruff; extra == "dev"
Requires-Dist: build; extra == "dev"
Dynamic: license-file
